{
    "Personal": {
        "Name": "Seu Nome da Silva Sauro",
        "birthDate": "1991-04-09",
        "birthDateSuffix": "anos",
        "nationality": "brasileiro",
        "civilStatus": "estado civil",
        "address": "Rua dos Bobos, No Zero",
        "cellphone": "11 5555-5555",
        "email": "seunome@dominio.com",
        "twitter": "@seunome",
        "github": "seunome",
        "disclaimer": "alguma coisa a declarar"
    },
    "Education": {
        "title": "Forma\u00e7\u00e3o",
        "value": [
            {
                "key": "Ensino Superior",
                "values": [
                    "Escola XXX YYY ZZZ"
                ]
            },
            {
                "key": "Escola X",
                "values": [
                    "Curso 1",
                    "Curso 2"
                ]
            }
        ]
    },
    "Knowledge": {
        "title": "Conhecimento",
        "value": [
            {
                "topic": "Arquitetura",
                "subtopic": [
                    { "key": "3DS Max", "value": 3 },
                    { "key": "Maya", "value": 3 },
                    { "key": "Blender", "value": 2 },
                    { "key": "ZBrush", "value": 1 },
                    { "key": "Vray", "value": 2 },
                    { "key": "Corona", "value": 1 }
                ]
            },
            {
                "topic": "Linguagens",
                "subtopic": [
                    { "key": "Elixir", "value": 3 },
                    { "key": "Javascript", "value": 3 },
                    { "key": "C#", "value": 3 },
                    { "key": "SCSS", "value": 2 },
                    { "key": "Python", "value": 1 }
                ]
            }
        ]
    },
    "Certification": {
        "title": "Certificado",
        "value": [
            {
                "key": "Certificado A4",
                "value": "AAAAA em BBBBB e depois CCCCC"
            }
        ]
    },
    "WorkExperience": {
        "title": "Experi\u00eancia",
        "value": [
            {
                "company": "Empresa do Tio João",
                "period_from": "2000-01-01",
                "period_to": "2014-10-20",
                "jobRole": "Fazedor de Coisas",
                "projects": [
                    {
                      "title": "Projeto 1",
                      "github": "seunome/projeto1",
                      "description": "||ABBR|Abreviação|| Adipisicing omnis doloremque consequuntur minus obcaecati! Accusantium exercitationem reiciendis reprehenderit"
                    },
                    {
                      "title": "Projeto 2",
                      "descriptions": [
                          {
                              "title": "Subprojeto 2.1",
                              "description": "Adipisicing #ênfase# omnis doloremque *itálico* **negrito** consequuntur minus obcaecati! Accusantium exercitationem reiciendis reprehenderit"
                          },
                          {
                              "title": "Subprojeto 2.2",
                              "description": "Adipisicing <um link|http://www.google.com> abc <um link github|https://github.com/umlinkqualquer> dfg <um link youtube|https://www.youtube.com/embed/4V_eoR6r1Tw?autoplay=1> hij <um gif|http://i.imgur.com/jE2v0Sl.gif> omnis <uma imagem|https://torange.biz/photo/18/18672/18672-FX-6-0-12-6-8-0.jpg> doloremque consequuntur minus obcaecati! Accusantium exercitationem reiciendis reprehenderit"
                          },
                          {
                              "title": "Subprojeto",
                              "description": "Adipisicing omnis doloremque consequuntur minus obcaecati! Accusantium exercitationem reiciendis reprehenderit"
                          }
                      ]
                    }
                ]
            },
            {
               "company": "Loja do Tio Pedro",
                "period_from": "2015-01-01",
                "period_to": "agora",
                "jobRole": "Eng. Contas",
                "projects": [
                  {
                    "title": "Projeto 1",
                    "description": "Adipisicing omnis doloremque consequuntur minus obcaecati! Accusantium exercitationem reiciendis reprehenderit"
                  }
                ]
            }
        ]
    }
}
